[
  { "day": 1, "title2": "The Mysterious Package" },
  { "day": 2, "title2": "Rebuilding the Sky" },
  { "day": 3, "title2": "Voices Beneath the Soil" },
  { "day": 4, "title2": "A Bridge Between Worlds" },
  { "day": 5, "title2": "The Last Lantern" },
  { "day": 6, "title2": "Dream Cartography" },
  { "day": 7, "title2": "When Machines Sleep" },
  { "day": 8, "title2": "The Seed Library" },
  { "day": 9, "title2": "Echoes of the River" },
  { "day": 10, "title2": "Forgotten Recipes" },
  { "day": 11, "title2": "The Whispering Forest" },
  { "day": 12, "title2": "Under the Glass Dome" },
  { "day": 13, "title2": "The Rewilders" },
  { "day": 14, "title2": "Solar Symphony" },
  { "day": 15, "title2": "Letters from the Future" },
  { "day": 16, "title2": "The Bioluminescent Garden" },
  { "day": 17, "title2": "The Day the Clouds Returned" },
  { "day": 18, "title2": "Archives of the Wind" },
  { "day": 19, "title2": "Caretakers of the Deep" },
  { "day": 20, "title2": "The Last Library" },
  { "day": 21, "title2": "Homes for the Birds" },
  { "day": 22, "title2": "The Firefly Network" },
  { "day": 23, "title2": "A World Without Roads" },
  { "day": 24, "title2": "The Compost Chronicles" },
  { "day": 25, "title2": "The Coral Cathedral" },
  { "day": 26, "title2": "Reclaiming the Ruins" },
  { "day": 27, "title2": "The Mushroom Bridge" },
  { "day": 28, "title2": "Citizen of the Forest" },
  { "day": 29, "title2": "The River That Remembered" },
  { "day": 30, "title2": "When We Learned to Listen" }
]
